jupyter_telemetry_sphinxext/__init__.py
jupyter_telemetry_sphinxext/__version__.py
jupyter_telemetry_sphinxext/app.py
jupyter_telemetry_sphinxext/directive.py
jupyter_telemetry_sphinxext-0.0.1.dist-info/METADATA
jupyter_telemetry_sphinxext-0.0.1.dist-info/WHEEL
jupyter_telemetry_sphinxext-0.0.1.dist-info/top_level.txt
jupyter_telemetry_sphinxext-0.0.1.dist-info/RECORD
