Metadata-Version: 2.1
Name: jupyter-telemetry-sphinxext
Version: 0.0.1
Summary: Sphinx extension for auto-generating Jupyter Telemetry schema documentation.
Home-page: https://github.com/Zsailer/jupyter_telemetry_sphinxext
Author: Jupyter Development Team
Author-email: jupyter@googlegroups.com
License: BSD
Platform: UNKNOWN
Classifier: Intended Audience :: Developers
Classifier: Intended Audience :: System Administrators
Classifier: Intended Audience :: Science/Research
Classifier: License :: OSI Approved :: BSD License
Classifier: Programming Language :: Python
Classifier: Programming Language :: Python :: 3
Requires-Python: >=3.5.0
Requires-Dist: jupyter-telemetry
Requires-Dist: sphinx-jsonschema
